afrc
