Metadata-Version: 2.4
Name: afrc
Version: 0.3.7
Summary: afrc is a Python package that implements an analytical version of the Flory Random Coil (i.e. the AFRC) for polypeptides.
Author-email: Alex Holehouse <alex.holehouse@wustl.edu>
License: LGPLv3
Requires-Python: >=3.7
License-File: LICENSE
Requires-Dist: numpy>=1.12.0
Requires-Dist: scipy
Provides-Extra: test
Requires-Dist: pytest>=6.1.2; extra == "test"
Dynamic: license-file
